src/__init__.py
src/main.py
tests/__init__.py
tests/test_add.py
istar_pycicd-1.0.4.dist-info/METADATA
istar_pycicd-1.0.4.dist-info/WHEEL
istar_pycicd-1.0.4.dist-info/top_level.txt
istar_pycicd-1.0.4.dist-info/RECORD
