Metadata-Version: 2.4
Name: istar_pycicd
Version: 1.0.4
Summary: Descripción de tu proyecto
Author: Istar Hernández
Author-email: istarhf110809@gmail.com
Requires-Dist: pytest
Requires-Dist: flake8
Dynamic: author
Dynamic: author-email
Dynamic: requires-dist
Dynamic: summary
